dw_core/__about__.py
dw_core/__init__.py
dw_core/config.py
dw_core/decorators.py
dw_core/dirs.py
dw_core/log.py
dw_core/models.py
dw_core/py.typed
dw_core/schema.py
dw_core/util.py
dw_core/schemas/bucket.json
dw_core/schemas/event.json
dw_core/schemas/export.json
dw_datastore/__init__.py
dw_datastore/benchmark.py
dw_datastore/datastore.py
dw_datastore/migration.py
dw_datastore/py.typed
dw_datastore/storages/__init__.py
dw_datastore/storages/abstract.py
dw_datastore/storages/memory.py
dw_datastore/storages/mongodb.py
dw_datastore/storages/peewee.py
dw_datastore/storages/sqlite.py
dw_query/__init__.py
dw_query/exceptions.py
dw_query/functions.py
dw_query/py.typed
dw_query/query2.py
dw_transform/__init__.py
dw_transform/chunk.py
dw_transform/chunk_events_by_key.py
dw_transform/classify.py
dw_transform/filter_keyvals.py
dw_transform/filter_period_intersect.py
dw_transform/flood.py
dw_transform/heartbeats.py
dw_transform/merge_events_by_keys.py
dw_transform/py.typed
dw_transform/simplify.py
dw_transform/sort_by.py
dw_transform/split_url_events.py
dw_transform/union_no_overlap.py
dw_core-0.0.3.dist-info/METADATA
dw_core-0.0.3.dist-info/WHEEL
dw_core-0.0.3.dist-info/top_level.txt
dw_core-0.0.3.dist-info/RECORD
