Metadata-Version: 2.1
Name: dw-core
Version: 0.0.3
Summary: Core library for DeskWatch
Home-page: https://deskwatch.net/
Author: Kohinoor Bharti
Author-email: kohinoorbharti7@gmail.com
License: UNKNOWN
Platform: UNKNOWN
Requires-Python: >=3.7,<4.0
Requires-Dist: TakeTheTime (<0.4.0,>=0.3.1)
Requires-Dist: appdirs (<2.0.0,>=1.4.3)
Requires-Dist: deprecation
Requires-Dist: iso8601 (<0.2.0,>=0.1.12)
Requires-Dist: jsonschema (<4.0,>=3.1)
Requires-Dist: peewee (<4.0.0,>=3.0.0)
Requires-Dist: python-json-logger
Requires-Dist: strict-rfc3339 (<0.8,>=0.7)
Requires-Dist: timeslot
Requires-Dist: tomlkit
Provides-Extra: mongo
Requires-Dist: pymongo (<4.0.0,>=3.10.0) ; extra == 'mongo'
